__init__.py
builDroid/__init__.py
builDroid/agents/__init__.py
builDroid/agents/agent.py
builDroid/agents/base.py
builDroid/app/main.py
builDroid/app/spinner.py
builDroid/commands/__init__.py
builDroid/commands/docker_helpers_static.py
builDroid/commands/execute_code.py
builDroid/commands/file_operations.py
builDroid/commands/gradle_build_error_solver.py
builDroid/commands/system.py
builDroid/config/__init__.py
builDroid/config/ai_config.py
builDroid/config/config.py
builDroid/files/Template.dockerfile
builDroid/files/__init__.py
builDroid/files/ai_settings.yaml
builDroid/files/gradle-wrapper.jar
builDroid/files/gradle-wrapper.properties
builDroid/files/gradlew
builDroid/logs/__init__.py
builDroid/logs/formatters.py
builDroid/logs/handlers.py
builDroid/logs/log_cycle.py
builDroid/logs/logger.py
builDroid/models/__init__.py
builDroid/models/command.py
builDroid/models/command_decorator.py
builDroid/models/command_parameter.py
builDroid/models/command_registry.py
builDroid/prompts/__init__.py
builDroid/prompts/generator.py
builDroid/prompts/prompt_files/cycle_instruction
builDroid/prompts/prompt_files/gradle_guidelines
builDroid/prompts/prompt_files/post_process_prompt
builDroid/utils/__init__.py
builDroid/utils/api_token_env.py
builDroid/utils/cleaner.py
builDroid/utils/git_utils.py
builDroid/utils/increment_experiment.py
builDroid/utils/json_utils.py
builDroid/utils/post_process.py
builDroid/utils/results_sheet.py
buildroid-1.3.4.dist-info/licenses/LICENSE
buildroid-1.3.4.dist-info/METADATA
buildroid-1.3.4.dist-info/WHEEL
buildroid-1.3.4.dist-info/entry_points.txt
buildroid-1.3.4.dist-info/top_level.txt
buildroid-1.3.4.dist-info/RECORD
