Metadata-Version: 2.4
Name: buildroid
Version: 1.3.4
Summary: Automation of Android Project Building with LLMs
Author-email: Jaehyeon Kim <jk7404@nyu.edu>
Project-URL: Homepage, https://github.com/jk7404/builDroid
Project-URL: Bug Tracker, https://github.com/jk7404/builDroid/issues
Classifier: Programming Language :: Python :: 3
Classifier: License :: OSI Approved :: MIT License
Classifier: Operating System :: OS Independent
Requires-Python: >=3.10
License-File: LICENSE
Requires-Dist: annotated-types==0.7.0
Requires-Dist: anyio==4.9.0
Requires-Dist: async-timeout==4.0.3
Requires-Dist: blis==1.3.0
Requires-Dist: cachetools==5.5.2
Requires-Dist: catalogue==2.0.10
Requires-Dist: certifi==2025.4.26
Requires-Dist: charset-normalizer==3.4.2
Requires-Dist: click==8.2.1
Requires-Dist: cloudpathlib==0.21.1
Requires-Dist: colorama==0.4.6
Requires-Dist: confection==0.1.5
Requires-Dist: cymem==2.0.11
Requires-Dist: distro==1.9.0
Requires-Dist: docker==7.1.0
Requires-Dist: debugpy==1.8.14
Requires-Dist: et-xmlfile==2.0.0
Requires-Dist: exceptiongroup==1.3.0
Requires-Dist: google-api-core==2.25.0
Requires-Dist: google-auth==2.40.2
Requires-Dist: google-genai==1.18.0
Requires-Dist: greenlet==3.2.2
Requires-Dist: h11==0.16.0
Requires-Dist: httpcore==1.0.9
Requires-Dist: httpx==0.28.1
Requires-Dist: idna==3.10
Requires-Dist: jinja2==3.1.6
Requires-Dist: jiter==0.10.0
Requires-Dist: jsonpatch==1.33
Requires-Dist: jsonpointer==3.0.0
Requires-Dist: jsonschema==4.24.0
Requires-Dist: langchain==0.3.25
Requires-Dist: langchain-core==0.3.63
Requires-Dist: langchain-text-splitters==0.3.8
Requires-Dist: langcodes==3.5.0
Requires-Dist: langsmith==0.3.43
Requires-Dist: language-data==1.3.0
Requires-Dist: marisa-trie==1.2.1
Requires-Dist: markdown-it-py==3.0.0
Requires-Dist: markupsafe==3.0.2
Requires-Dist: mdurl==0.1.2
Requires-Dist: murmurhash==1.0.13
Requires-Dist: numpy==2.2.6
Requires-Dist: openai==1.82.1
Requires-Dist: openpyxl==3.1.5
Requires-Dist: orjson==3.10.18
Requires-Dist: packaging==24.2
Requires-Dist: pandas==2.2.3
Requires-Dist: preshed==3.0.10
Requires-Dist: pyasn1==0.6.1
Requires-Dist: pyasn1-modules==0.4.2
Requires-Dist: pydantic==2.11.5
Requires-Dist: pydantic-core==2.33.2
Requires-Dist: pygments==2.19.1
Requires-Dist: python-dateutil==2.9.0.post0
Requires-Dist: python-dotenv==1.1.0
Requires-Dist: pytz==2025.2
Requires-Dist: pyyaml==6.0.2
Requires-Dist: requests==2.32.3
Requires-Dist: requests-toolbelt==1.0.0
Requires-Dist: rich==14.0.0
Requires-Dist: rsa==4.9.1
Requires-Dist: shellingham==1.5.4
Requires-Dist: six==1.17.0
Requires-Dist: smart-open==7.1.0
Requires-Dist: sniffio==1.3.1
Requires-Dist: spacy==3.8.7
Requires-Dist: spacy-legacy==3.0.12
Requires-Dist: spacy-loggers==1.0.5
Requires-Dist: sqlalchemy==2.0.41
Requires-Dist: srsly==2.5.1
Requires-Dist: tenacity==9.1.2
Requires-Dist: thinc==8.3.6
Requires-Dist: tqdm==4.67.1
Requires-Dist: typer==0.16.0
Requires-Dist: typing-extensions==4.13.2
Requires-Dist: typing-inspection==0.4.1
Requires-Dist: tzdata==2025.2
Requires-Dist: urllib3==2.4.0
Requires-Dist: wasabi==1.1.3
Requires-Dist: weasel==0.4.1
Requires-Dist: websockets==15.0.1
Requires-Dist: wrapt==1.17.2
Requires-Dist: zstandard==0.23.0
Dynamic: license-file
